{"rows":[{"strike":9000,"callLtp":0,"putLtp":0,"callOi":0,"putOi":0,"iv":0},{"strike":10000,"callLtp":0,"putLtp":0,"callOi":0,"putOi":0,"iv":0},{"strike":11000,"callLtp":0,"putLtp":0,"callOi":0,"putOi":0,"iv":0},{"strike":12000,"callLtp":0,"putLtp":0,"callOi":0,"putOi":0,"iv":0},{"strike":13000,"callLtp":0,"putLtp":6.5,"callOi":0,"putOi":7325,"iv":0},{"strike":14000,"callLtp":0,"putLtp":0,"callOi":0,"putOi":0,"iv":0},{"strike":15000,"callLtp":0,"putLtp":8,"callOi":0,"putOi":6750,"iv":0},{"strike":16000,"callLtp":0,"putLtp":8.85,"callOi":0,"putOi":5275,"iv":0},{"strike":16500,"callLtp":0,"putLtp":10.95,"callOi":0,"putOi":3000,"iv":0},{"strike":17000,"callLtp":7010,"putLtp":11.6,"callOi":0,"putOi":36800,"iv":0},{"strike":18000,"callLtp":6999,"putLtp":16.55,"callOi":60625,"putOi":132950,"iv":0},{"strike":19000,"callLtp":6000,"putLtp":24.85,"callOi":10625,"putOi":151900,"iv":0},{"strike":19500,"callLtp":5980,"putLtp":0,"callOi":0,"putOi":0,"iv":30.26663664296673},{"strike":20000,"callLtp":5090,"putLtp":36,"callOi":288175,"putOi":846675,"iv":0},{"strike":21000,"callLtp":4126.35,"putLtp":48.45,"callOi":191275,"putOi":935325,"iv":0},{"strike":22000,"callLtp":3202.45,"putLtp":80,"callOi":441025,"putOi":1703750,"iv":0},{"strike":23000,"callLtp":2302.35,"putLtp":148.9,"callOi":463950,"putOi":2091100,"iv":0},{"strike":24000,"callLtp":1475,"putLtp":303,"callOi":1009025,"putOi":3322450,"iv":0},{"strike":25000,"callLtp":816.95,"putLtp":612,"callOi":1417525,"putOi":2269400,"iv":8.215008405793466},{"strike":26000,"callLtp":375.4,"putLtp":1137.25,"callOi":2674675,"putOi":1425800,"iv":9.135840827308686},{"strike":27000,"callLtp":147.3,"putLtp":1894.5,"callOi":1861975,"putOi":767625,"iv":9.666077318231196},{"strike":28000,"callLtp":60.15,"putLtp":2752.1,"callOi":1521425,"putOi":782000,"iv":10.49405085255093},{"strike":29000,"callLtp":29.25,"putLtp":3700,"callOi":669625,"putOi":181325,"iv":11.607385485665443},{"strike":30000,"callLtp":16,"putLtp":4646.45,"callOi":482400,"putOi":92050,"iv":12.752182356991018},{"strike":31000,"callLtp":10.5,"putLtp":0,"callOi":242725,"putOi":0,"iv":14.05240277433006},{"strike":32000,"callLtp":0,"putLtp":0,"callOi":0,"putOi":0,"iv":1.1546604274457963},{"strike":33000,"callLtp":0,"putLtp":0,"callOi":0,"putOi":0,"iv":1.3130492090913637},{"strike":34000,"callLtp":0,"putLtp":0,"callOi":0,"putOi":0,"iv":1.466652209620629},{"strike":35000,"callLtp":0,"putLtp":0,"callOi":0,"putOi":0,"iv":1.6157452861004538},{"strike":36000,"callLtp":0,"putLtp":0,"callOi":0,"putOi":0,"iv":1.760581114606393},{"strike":37000,"callLtp":0,"putLtp":0,"callOi":0,"putOi":0,"iv":1.901391724207779},{"strike":38000,"callLtp":0,"putLtp":0,"callOi":0,"putOi":0,"iv":2.0404265415702527},{"strike":39000,"callLtp":0,"putLtp":0,"callOi":0,"putOi":0,"iv":2.1739434280593635},{"strike":40000,"callLtp":0,"putLtp":0,"callOi":0,"putOi":0,"iv":2.3040242704596317},{"strike":41000,"callLtp":0,"putLtp":0,"callOi":0,"putOi":0,"iv":2.430838124019395}],"lastPrice":24631.30078125,"futClose":26405.1,"ltpTs":1755264442805,"oiTs":1755264442805,"source":"fresh","savedAt":1755264442866,"provider":"dhan","symbol":"NIFTY","expiry":"2025-12-30"}